funlab/flaskr/__init__.py
funlab/flaskr/app.py
funlab/flaskr/conf/__init__.py
funlab/flaskr/conf/config.toml
funlab/flaskr/conf/gunicorn_conf.py
funlab/flaskr/conf/waitress_conf.py
funlab/flaskr/static/brands/amazon.svg
funlab/flaskr/static/brands/android.svg
funlab/flaskr/static/brands/app-store.svg
funlab/flaskr/static/brands/apple-podcast.svg
funlab/flaskr/static/brands/apple.svg
funlab/flaskr/static/brands/behance.svg
funlab/flaskr/static/brands/discord.svg
funlab/flaskr/static/brands/dribbble.svg
funlab/flaskr/static/brands/dropbox.svg
funlab/flaskr/static/brands/ever-green.svg
funlab/flaskr/static/brands/facebook.svg
funlab/flaskr/static/brands/figma.svg
funlab/flaskr/static/brands/font-awesome.svg
funlab/flaskr/static/brands/gitlab.svg
funlab/flaskr/static/brands/google-ads.svg
funlab/flaskr/static/brands/google-adsense.svg
funlab/flaskr/static/brands/google-analytics.svg
funlab/flaskr/static/brands/google-cloud.svg
funlab/flaskr/static/brands/google-drive.svg
funlab/flaskr/static/brands/google-fit.svg
funlab/flaskr/static/brands/google-home.svg
funlab/flaskr/static/brands/google-maps.svg
funlab/flaskr/static/brands/google-meet.svg
funlab/flaskr/static/brands/google-photos.svg
funlab/flaskr/static/brands/google-play.svg
funlab/flaskr/static/brands/google-shopping.svg
funlab/flaskr/static/brands/google-teams.svg
funlab/flaskr/static/brands/google.svg
funlab/flaskr/static/brands/instagram.svg
funlab/flaskr/static/brands/klarna.svg
funlab/flaskr/static/brands/linkedin.svg
funlab/flaskr/static/brands/mailchimp.svg
funlab/flaskr/static/brands/medium.svg
funlab/flaskr/static/brands/messenger.svg
funlab/flaskr/static/brands/meta.svg
funlab/flaskr/static/brands/monday.svg
funlab/flaskr/static/brands/netflix.svg
funlab/flaskr/static/brands/notion.svg
funlab/flaskr/static/brands/office-365.svg
funlab/flaskr/static/brands/opera.svg
funlab/flaskr/static/brands/paypal.svg
funlab/flaskr/static/brands/petreon.svg
funlab/flaskr/static/brands/pinterest.svg
funlab_flaskr-0.3.7.dist-info/LICENSE
funlab_flaskr-0.3.7.dist-info/METADATA
funlab_flaskr-0.3.7.dist-info/WHEEL
funlab_flaskr-0.3.7.dist-info/RECORD
