Metadata-Version: 2.1
Name: funlab-flaskr
Version: 0.3.7
Summary: Funlab - A pluggable flask application framework.
License: MIT
Author: sunny
Author-email: 013.lin@gmail.com
Requires-Python: >=3.11,<4.0
Classifier: License :: OSI Approved :: MIT License
Classifier: Programming Language :: Python :: 3
Classifier: Programming Language :: Python :: 3.11
Requires-Dist: flask (>=3.0.0,<4.0.0)
Requires-Dist: flask-login (>=0.6.3,<0.7.0)
Requires-Dist: funlab-libs (>=0.3.6,<0.4.0)
